pyptp/__init__.py
pyptp/_credentials.py
pyptp/network_lv.py
pyptp/network_mv.py
pyptp/ptp_log.py
pyptp/IO/exporters/__init__.py
pyptp/IO/exporters/gnf_exporter.py
pyptp/IO/exporters/ipysigma_exporter.py
pyptp/IO/exporters/json_exporter.py
pyptp/IO/exporters/vnf_exporter.py
pyptp/IO/importers/__init__.py
pyptp/IO/importers/_base_handler.py
pyptp/IO/importers/_strategies.py
pyptp/IO/importers/gnf_importer.py
pyptp/IO/importers/json_helper.py
pyptp/IO/importers/vnf_importer.py
pyptp/IO/importers/_gnf_handlers/__init__.py
pyptp/IO/importers/_gnf_handlers/async_generator_handler.py
pyptp/IO/importers/_gnf_handlers/async_motor_handler.py
pyptp/IO/importers/_gnf_handlers/battery_handler.py
pyptp/IO/importers/_gnf_handlers/cable_handler.py
pyptp/IO/importers/_gnf_handlers/circuit_breaker_handler.py
pyptp/IO/importers/_gnf_handlers/comment_handler.py
pyptp/IO/importers/_gnf_handlers/earthing_transformer_handler.py
pyptp/IO/importers/_gnf_handlers/frame_handler.py
pyptp/IO/importers/_gnf_handlers/fuse_handler.py
pyptp/IO/importers/_gnf_handlers/gm_type_handler.py
pyptp/IO/importers/_gnf_handlers/home_handler.py
pyptp/IO/importers/_gnf_handlers/legend_handler.py
pyptp/IO/importers/_gnf_handlers/link_handler.py
pyptp/IO/importers/_gnf_handlers/load_handler.py
pyptp/IO/importers/_gnf_handlers/load_switch_handler.py
pyptp/IO/importers/_gnf_handlers/measure_field_handler.py
pyptp/IO/importers/_gnf_handlers/node_handler.py
pyptp/IO/importers/_gnf_handlers/profile_handler.py
pyptp/IO/importers/_gnf_handlers/properties_handler.py
pyptp/IO/importers/_gnf_handlers/pv_handler.py
pyptp/IO/importers/_gnf_handlers/reactance_coil_handler.py
pyptp/IO/importers/_gnf_handlers/selection_handler.py
pyptp/IO/importers/_gnf_handlers/sheet_handler.py
pyptp/IO/importers/_gnf_handlers/shunt_capacitor_handler.py
pyptp/IO/importers/_gnf_handlers/source_handler.py
pyptp/IO/importers/_gnf_handlers/special_transformer_handler.py
pyptp/IO/importers/_gnf_handlers/sync_generator_handler.py
pyptp-0.0.22.dist-info/METADATA
pyptp-0.0.22.dist-info/WHEEL
pyptp-0.0.22.dist-info/licenses/LICENSE
pyptp-0.0.22.dist-info/RECORD
