Metadata-Version: 2.4
Name: pyptp
Version: 0.0.22
Summary: Open-source Python SDK for electrical grid calculations and modelling
Author-email: Phase to Phase <pyptp@phasetophase.com>
License: GPL-3.0-or-later
License-File: LICENSE
Keywords: distribution-networks,dso,electrical-engineering,gaia,grid-calculations,low-voltage,medium-voltage,network-modeling,power-systems,vision
Classifier: Development Status :: 3 - Alpha
Classifier: Intended Audience :: Developers
Classifier: Intended Audience :: Science/Research
Classifier: Intended Audience :: System Administrators
Classifier: License :: OSI Approved :: GNU General Public License v3 or later (GPLv3+)
Classifier: Operating System :: OS Independent
Classifier: Programming Language :: Python :: 3
Classifier: Programming Language :: Python :: 3.11
Classifier: Programming Language :: Python :: 3.12
Classifier: Programming Language :: Python :: 3.13
Classifier: Topic :: Scientific/Engineering
Classifier: Topic :: Software Development :: Libraries :: Python Modules
Classifier: Typing :: Typed
Requires-Python: >=3.11
Requires-Dist: dataclasses-json<1,>=0.6.7
Requires-Dist: loguru<1,>=0.7
Requires-Dist: networkx<4,>=3.4.2
Requires-Dist: openpyxl<4,>=3.1.5
Requires-Dist: pandas<3,>=2.2.3
Requires-Dist: pydantic-settings<3,>=2.0
Requires-Dist: requests<3,>=2.31.0
